minisklearn/__init__.py
minisklearn/base/__init__.py
minisklearn/base/base.py
minisklearn/cluster/__init__.py
minisklearn/cluster/cluster.py
minisklearn/covariance/__init__.py
minisklearn/covariance/covariance.py
minisklearn/decomposition/__init__.py
minisklearn/decomposition/decomposition.py
minisklearn/ensemble/__init__.py
minisklearn/ensemble/ensemble.py
minisklearn/feature_extraction/__init__.py
minisklearn/feature_extraction/feature_extraction.py
minisklearn/feature_selection/__init__.py
minisklearn/feature_selection/feature_selection.py
minisklearn/impute/__init__.py
minisklearn/impute/imputer.py
minisklearn/linear_model/__init__.py
minisklearn/linear_model/linear_model.py
minisklearn/meta/__init__.py
minisklearn/meta/meta_estimators.py
minisklearn/metrics/__init__.py
minisklearn/metrics/distances.py
minisklearn/metrics/errors.py
minisklearn/metrics/kernels.py
minisklearn/metrics/metrics.py
minisklearn/model_selection/__init__.py
minisklearn/model_selection/model_selection.py
minisklearn/naive_bayes/__init__.py
minisklearn/naive_bayes/naive_bayes.py
minisklearn/neighbors/__init__.py
minisklearn/neighbors/neighbors.py
minisklearn/neural_network/__init__.py
minisklearn/neural_network/neural_network.py
minisklearn/pipeline/__init__.py
minisklearn/pipeline/pipeline.py
minisklearn/preprocessing/__init__.py
minisklearn/preprocessing/encoding.py
minisklearn/preprocessing/scaling.py
minisklearn/svm/__init__.py
minisklearn/svm/svm.py
minisklearn/tree/__init__.py
minisklearn/tree/nodes.py
minisklearn/tree/tree.py
minisklearn-0.1.3.dist-info/METADATA
minisklearn-0.1.3.dist-info/WHEEL
minisklearn-0.1.3.dist-info/top_level.txt
minisklearn-0.1.3.dist-info/RECORD
