Metadata-Version: 2.1
Name: minisklearn
Version: 0.1.3
Summary: Mini Scikit Learn
Home-page: https://github.com/AymanYouss/mini-scikit-learn
Author: Ayman Youss & Amine Idrissi
Author-email: ayman.youss@um6p.ma
Classifier: Programming Language :: Python :: 3
Classifier: License :: OSI Approved :: MIT License
Classifier: Operating System :: OS Independent
Requires-Python: >=3.6
Requires-Dist: numpy
Requires-Dist: scipy
